bevigil/__init__.py
bevigil/cli.py
bevigil/enumerator.py
bevigil/exceptions.py
bevigil/helpers.py
bevigil/settings.py
bevigil_cli-1.0.14.dist-info/LICENSE
bevigil_cli-1.0.14.dist-info/METADATA
bevigil_cli-1.0.14.dist-info/WHEEL
bevigil_cli-1.0.14.dist-info/entry_points.txt
bevigil_cli-1.0.14.dist-info/top_level.txt
bevigil_cli-1.0.14.dist-info/RECORD
