Metadata-Version: 2.1
Name: bevigil-cli
Version: 1.0.14
Summary: BeVigil OSINT CLI
Home-page: https://osint.bevigil.com/
Author: Bevigil
Author-email: bevigil@cloudsek.com
License: Apache License 2.0
Classifier: Programming Language :: Python :: 3
Classifier: License :: OSI Approved :: Apache Software License
Classifier: Operating System :: OS Independent
Requires-Python: >=3.8
License-File: LICENSE
Requires-Dist: certifi (>=2021.5.30)
Requires-Dist: charset-normalizer (>=2.0.8)
Requires-Dist: click (>=8.1.0)
Requires-Dist: idna (>=3.1)
Requires-Dist: requests (>=2.27.0)
